log/__init__.py
log/filters.py
log/helpers.py
log/logger.py
log/py.typed
log/settings.py
log/state.py
log/tests/__init__.py
log/tests/conftest.py
log/tests/test_api.py
log/tests/test_helpers.py
log/tests/test_logger.py
log/tests/test_utils.py
log/utils.py
minilog-2.3.1.dist-info/LICENSE.md
minilog-2.3.1.dist-info/METADATA
minilog-2.3.1.dist-info/WHEEL
minilog-2.3.1.dist-info/RECORD
