Metadata-Version: 2.1
Name: minilog
Version: 2.3.1
Summary: Minimalistic wrapper for Python logging.
Home-page: https://pypi.org/project/minilog
License: MIT
Keywords: logging
Author: Jace Browning
Author-email: jacebrowning@gmail.com
Requires-Python: >=3.8,<4.0
Classifier: Development Status :: 5 - Production/Stable
Classifier: Intended Audience :: Developers
Classifier: License :: OSI Approved :: MIT License
Classifier: Natural Language :: English
Classifier: Operating System :: OS Independent
Classifier: Programming Language :: Python
Classifier: Programming Language :: Python :: 3
Classifier: Programming Language :: Python :: 3.8
Classifier: Programming Language :: Python :: 3.9
Classifier: Programming Language :: Python :: 3.10
Classifier: Programming Language :: Python :: 3.11
Classifier: Programming Language :: Python :: 3.12
Classifier: Topic :: Software Development
Classifier: Topic :: System :: Logging
Project-URL: Documentation, https://minilog.readthedocs.io
Project-URL: Repository, https://github.com/jacebrowning/minilog
